<?xml version="1.0" encoding="utf-8"?>
<main>
	<heading1> PHP Comments</heading1>
	<text>
		<heading2>Comments in PHP</heading2>
		<para>A comment in PHP code is a line that is not executed as a part of the program. Its only purpose is to be read by someone who is looking at the code.</para>
		<list>
			<li_title>Comments can be used to:</li_title>
			<item>Let others understand your code</item>
			<item>Remind yourself of what you did - Most programmers have experienced coming back to their own work a year or two later and having to re-figure out what they did. Comments can remind you of what you were thinking when you wrote the code</item>
		</list>
		<para>PHP supports several ways of commenting:</para>
	</text>
	<editor>
		<title>Example:</title>
		<dis>Syntax for comments:</dis>
		<syntax><![CDATA[<?php
// This is a single-line comment

# This is also a single-line comment
				
/*
This is a multiple-lines comment block
that spans over multiple
lines
*/
				
// You can also use comments to leave out parts of a code line
$x = 5 /* + 15 */ + 5;
echo $x;
?>]]></syntax>
	</editor>
</main>